pyparinya/__init__.py
pyparinya-0.0.3.dist-info/METADATA
pyparinya-0.0.3.dist-info/RECORD
pyparinya-0.0.3.dist-info/WHEEL
pyparinya-0.0.3.dist-info/top_level.txt
