Metadata-Version: 2.1
Name: pyparinya
Version: 0.0.3
Summary: A collection of my codes
Home-page: UNKNOWN
Author: Parinya Sanguansat
Author-email: sanguansat@yahoo.com
License: UNKNOWN
Platform: UNKNOWN
Classifier: Programming Language :: Python :: 3
Classifier: License :: OSI Approved :: MIT License
Classifier: Operating System :: OS Independent
